terranet/__init__.py
terranet/config_api.py
terranet/controller.py
terranet/event.py
terranet/link.py
terranet/net.py
terranet/router_config.py
terranet/simulator.py
terranet/examples/__init__.py
terranet/examples/run_hybrid_backup_net.py
terranet/examples/run_virtual_fiber_net.py
terranet/influx/__init__.py
terranet/influx/customerstats.py
terranet/influx/switchstats.py
terranet/node/__init__.py
terranet/node/iperf.py
terranet/node/router.py
terranet/node/terranode.py
terranet/node/wifi.py
terranet/proxy/__init__.py
terranet/proxy/namespace_proxy.py
terranet/proxy/namespace_proxy_plugin.py
terranet/ryu/__init__.py
terranet/ryu/app/__init__.py
terranet/ryu/app/channel_assignment_oracle.py
terranet/ryu/app/customer_allocation_monitor.py
terranet/ryu/app/customer_flow_pipeline.py
terranet/ryu/app/customer_stats_monitor.py
terranet/ryu/app/ipv6_address_helper.py
terranet/ryu/app/mac_learning_pipeline.py
terranet/ryu/app/cfg/channel_oracle.conf
terranet/simulation/__init__.py
terranet/simulation/simulate_channel_oracle.py
terranet/simulation/simulate_customer_arrivals.py
terranet/simulation/simulate_hybrid_handover.py
terranet/topo/__init__.py
terranet/topo/backup.py
terranet/topo/terratopo.py
terranet/topo/virtual_fiber.py
terranet/topo/.komondor/HybridBackupTerragraphTopo/input/000.cfg
terranet/topo/.komondor/HybridBackupTerragraphTopo/input/001.cfg
terranet/topo/.komondor/HybridBackupTerragraphTopo/input/002.cfg
terranet/topo/.komondor/HybridBackupTerragraphTopo/input/003.cfg
terranet/topo/.komondor/HybridBackupTerragraphTopo/input/004.cfg
terranet/topo/.komondor/HybridBackupTerragraphTopo/input/005.cfg
terranet/topo/.komondor/HybridBackupTerragraphTopo/input/006.cfg
terranet/topo/.komondor/HybridBackupTerragraphTopo/input/007.cfg
terranet/topo/.komondor/HybridBackupTerragraphTopo/input/008.cfg
terranet/topo/.komondor/HybridBackupTerragraphTopo/input/009.cfg
terranet/topo/.komondor/HybridBackupTerragraphTopo/input/010.cfg
terranet-0.2.1.dist-info/LICENSE
terranet-0.2.1.dist-info/METADATA
terranet-0.2.1.dist-info/WHEEL
terranet-0.2.1.dist-info/top_level.txt
terranet-0.2.1.dist-info/RECORD
