Metadata-Version: 2.1
Name: terranet
Version: 0.2.1
Summary: Terranet: mmWave Distribution Network Emulator
Home-page: UNKNOWN
Author: butjar
Author-email: UNKNOWN
License: UNKNOWN
Keywords: terranet terragraph wifi wifi6 60GHz mmWave
Platform: UNKNOWN
Requires-Dist: collectd
Requires-Dist: configparser
Requires-Dist: Flask
Requires-Dist: influxdb
Requires-Dist: netns
Requires-Dist: numpy
Requires-Dist: proxy.py
Requires-Dist: requests
Requires-Dist: ryu
Requires-Dist: whichcraft
